micropython_bmp581/__init__.py
micropython_bmp581/bmp581.py
micropython_bmp581/i2c_helpers.py
micropython_bmp581-0.1.3.dist-info/LICENSE
micropython_bmp581-0.1.3.dist-info/METADATA
micropython_bmp581-0.1.3.dist-info/WHEEL
micropython_bmp581-0.1.3.dist-info/top_level.txt
micropython_bmp581-0.1.3.dist-info/RECORD
