Metadata-Version: 2.1
Name: micropython-bmp581
Version: 0.1.3
Summary: MicroPython Driver for the Bosch BMP581 pressure sensor
Author-email: JDM <xxyx@mailmeto.mozmail.com>
License: MIT
Project-URL: Homepage, https://github.com/jposada202020/MicroPython_BMP581
Keywords: sensor,micropython,pressure,bosch,bmp581,altitude,temperature
Classifier: Intended Audience :: Developers
Classifier: Topic :: Software Development :: Libraries
Classifier: Topic :: Software Development :: Embedded Systems
Classifier: Topic :: System :: Hardware
Classifier: License :: OSI Approved :: MIT License
Classifier: Programming Language :: Python :: Implementation :: MicroPython
License-File: LICENSE
